[
    {
        "title": "에어 포스 1 '07",
        "theme": "Fresh",
        "image": "https://secure-images.nike.com/is/image/DotCom/DM0211_001_A_PREM?$SNKRS_COVER_WD$&align=0,1",
        "href": "/kr/launch/t/air-force-1-07-fresh-ho22?size=8.5",
        "date": "11/14",
        "releaseDate": "2022-11-14 01:00"
    },
    {
        "title": "에어맥스 TW",
        "theme": "Light Bone and Red Clay",
        "image": "https://secure-images.nike.com/is/image/DotCom/DQ3984_002_A_PREM?$SNKRS_COVER_WD$&align=0,1",
        "href": "/kr/launch/t/air-max-tw-light-bone-and-red-clay?size=8.5",
        "date": "11/15",
        "releaseDate": "2022-11-15 01:00"
    },
    {
        "title": "우먼스 에어맥스 95",
        "theme": "Mars Stone",
        "image": "https://secure-images.nike.com/is/image/DotCom/DZ4710_200_A_PREM?$SNKRS_COVER_WD$&align=0,1",
        "href": "/kr/launch/t/womens-air-max-95-mars-stone?size=8.5",
        "date": "11/15",
        "releaseDate": "2022-11-15 01:00"
    },
    {
        "title": "터미네이터 하이",
        "theme": "Granite and Dark Obsidian",
        "image": "https://secure-images.nike.com/is/image/DotCom/FB1832_001_A_PREM?$SNKRS_COVER_WD$&align=0,1",
        "href": "/kr/launch/t/terminator-high-granite-dark-obsidian?size=8.5",
        "date": "11/17",
        "releaseDate": "2022-11-17 01:00"
    },
    {
        "title": "우먼스 에어 포스 1 '07 미드",
        "theme": "Tokyo 03",
        "image": "https://secure-images.nike.com/is/image/DotCom/DZ4865_503_A_PREM?$SNKRS_COVER_WD$&align=0,1",
        "href": "/kr/launch/t/womens-air-force-1-07-mid-tokyo-03?size=8.5",
        "date": "11/18",
        "releaseDate": "2022-11-18 01:00"
    },
    {
        "title": "에어 트레이너 1",
        "theme": "Tokyo 03",
        "image": "https://secure-images.nike.com/is/image/DotCom/DZ4867_010_A_PREM?$SNKRS_COVER_WD$&align=0,1",
        "href": "/kr/launch/t/air-trainer-1-tokyo-03?size=8.5",
        "date": "11/18",
        "releaseDate": "2022-11-18 01:00"
    },
    {
        "title": "에어 조던 6",
        "theme": "Metallic Silver",
        "image": "https://secure-images.nike.com/is/image/DotCom/DX2836_001_A_PREM?$SNKRS_COVER_WD$&align=0,1",
        "href": "/kr/launch/t/air-jordan-6-metallic-silver?size=8.5",
        "date": "11/19",
        "releaseDate": "2022-11-19 01:00"
    },
    {
        "title": "나이키 SB 덩크 로우 ",
        "theme": "HUF SF",
        "image": "https://secure-images.nike.com/is/image/DotCom/FD8775_001_A_PREM?$SNKRS_COVER_WD$&align=0,1",
        "href": "/kr/launch/t/nike-sb-dunk-low-huf-sf?size=8.5",
        "date": "11/22",
        "releaseDate": "2022-11-22 01:00"
    },
    {
        "title": "나이키 SB 덩크 로우",
        "theme": "HUF NY",
        "image": "https://secure-images.nike.com/is/image/DotCom/FD8775_100_A_PREM?$SNKRS_COVER_WD$&align=0,1",
        "href": "/kr/launch/t/nike-sb-dunk-low-huf-ny?size=8.5",
        "date": "11/22",
        "releaseDate": "2022-11-22 01:00"
    },
    {
        "title": "에어 조던 1 (Big Kids)",
        "theme": "Chicago",
        "image": "https://secure-images.nike.com/is/image/DotCom/FD1437_612_A_PREM?$SNKRS_COVER_WD$&align=0,1",
        "href": "/kr/launch/t/air-jordan-1-chicago1-gs-kr?size=8.5",
        "date": "11/24",
        "releaseDate": "2022-11-24 01:00"
    },
    {
        "title": "조던 1 (Little Kids)",
        "theme": "Chicago",
        "image": "https://secure-images.nike.com/is/image/DotCom/FD1412_612_A_PREM?$SNKRS_COVER_WD$&align=0,1",
        "href": "/kr/launch/t/jordan-1-chicago1-ps-kr?size=8.5",
        "date": "11/24",
        "releaseDate": "2022-11-24 01:00"
    },
    {
        "title": "에어 조던 1",
        "theme": "Chicago",
        "image": "https://secure-images.nike.com/is/image/DotCom/DZ5485_612_A_PREM?$SNKRS_COVER_WD$&align=0,1",
        "href": "/kr/launch/t/air-jordan-1-chicago1?size=8.5",
        "date": "11/24",
        "releaseDate": "2022-11-24 01:00"
    },
    {
        "title": "조던 1 (Toddler)",
        "theme": "Chicago",
        "image": "https://secure-images.nike.com/is/image/DotCom/FD1413_612_A_PREM?$SNKRS_COVER_WD$&align=0,1",
        "href": "/kr/launch/t/jordan-1-chicago1-td-kr?size=8.5",
        "date": "11/24",
        "releaseDate": "2022-11-24 01:00"
    }
]
